libtestzechatt-0.1.9.dist-info/METADATA
libtestzechatt-0.1.9.dist-info/WHEEL
libtestzechatt-0.1.9.dist-info/entry_points.txt
simplesocialauthlib/__init__.py
simplesocialauthlib/abstract.py
simplesocialauthlib/exceptions.py
simplesocialauthlib/providers/__init__.py
simplesocialauthlib/providers/github.py
simplesocialauthlib/providers/google.py
simplesocialauthlib/types.py
simplesocialauthlib/utils.py
libtestzechatt-0.1.9.dist-info/RECORD
