Metadata-Version: 2.1
Name: LibTestZechatt
Version: 0.1.9
Summary: SimpleSocialAuthLib is a lightweight and easy-to-use Python library that simplifies OAuth2 authentication integration with social providers such as Google, GitHub, Facebook, Twitter, and more.
Author-Email: Macktireh <abdimack97@gmail.com>
License: MIT
Classifier: Programming Language :: Python
Classifier: Programming Language :: Python :: 3
Classifier: Programming Language :: Python :: 3.12
Classifier: License :: OSI Approved :: MIT License
Classifier: Operating System :: OS Independent
Classifier: Intended Audience :: Developers
Classifier: Topic :: Software Development :: Libraries
Project-URL: Homepage, https://github.com/Macktireh/SimpleSocialAuthLib
Project-URL: Repository, https://github.com/Macktireh/SimpleSocialAuthLib
Project-URL: Documentation, https://github.com/Macktireh/SimpleSocialAuthLib
Project-URL: Issues, https://github.com/Macktireh/SimpleSocialAuthLib/issues
Requires-Python: >=3.12
Requires-Dist: google-api-python-client>=2.147.0
Requires-Dist: requests-oauthlib>=2.0.0
